<?xml version="1.0" encoding="UTF-8"?>
<MediaContainer size="27" allowSync="1" art="/:/resources/movie-fanart.jpg" identifier="com.plexapp.plugins.library"
                librarySectionID="4" librarySectionTitle="Best Movies"
                librarySectionUUID="4f7abfee-824d-485b-906a-27c917e222d5" mediaTagPrefix="/system/bundle/media/flags/"
                mediaTagVersion="1615295203" thumb="/:/resources/movie.png" title1="Best Movies"
                title2="All Best Movies" viewGroup="movie" viewMode="65592">
    <Video ratingKey="48505" key="/library/metadata/48505" guid="plex://movie/5d776a3cad5437001f7769e8"
           studio="DC Comics" type="movie" title="Batman v Superman: Dawn of Justice" contentRating="PG-13"
           summary="Fearing the actions of a god-like Super Hero left unchecked, Gotham City&#8217;s own formidable, forceful vigilante takes on Metropolis&#8217;s most revered, modern-day savior, while the world wrestles with what sort of hero it really needs. And with Batman and Superman at war with one another, a new threat quickly arises, putting mankind in greater danger than it&#8217;s ever known before."
           rating="2.8" audienceRating="6.2" year="2016" tagline="Justice or revenge"
           thumb="/library/metadata/48505/thumb/1601864979" art="/library/metadata/48505/art/1601864979"
           duration="10953673" originallyAvailableAt="2016-03-19" addedAt="1516287600" updatedAt="1601864979"
           audienceRatingImage="rottentomatoes://image.rating.upright" chapterSource="media"
           primaryExtraKey="/library/metadata/48507" ratingImage="rottentomatoes://image.rating.rotten">
        <Media id="72951" duration="10953673" bitrate="34950" width="1920" height="1080" aspectRatio="1.78"
               audioChannels="8" audioCodec="dca-ma" videoCodec="h264" videoResolution="1080" container="mkv"
               videoFrameRate="24p" audioProfile="ma" videoProfile="high">
            <Part id="73015" key="/library/parts/73015/1516287600/file.mkv" duration="10953673"
                  file="/data/gaps/Best Movies/Batman v Superman Dawn of Justice (2016)/Batman v Superman Dawn of Justice (2016).mkv"
                  size="47804540207" audioProfile="ma" container="mkv" hasThumbnail="1" indexes="sd"
                  videoProfile="high"/>
        </Media>
        <Genre tag="Action/Adventure"/>
        <Genre tag="Fantasy"/>
        <Director tag="Zack Snyder"/>
        <Writer tag="David S. Goyer"/>
        <Writer tag="Frank Miller"/>
        <Country tag="United States of America"/>
        <Role tag="Ben Affleck"/>
        <Role tag="Henry Cavill"/>
        <Role tag="Jesse Eisenberg"/>
    </Video>
    <Video ratingKey="48534" key="/library/metadata/48534" guid="plex://movie/5d7770b9594b2b001e750506"
           studio="Warner Bros. Animation" type="movie" title="Batman vs Teenage Mutant Ninja Turtles"
           contentRating="PG-13"
           summary="Batman, Batgirl and Robin forge an alliance with the Teenage Mutant Ninja Turtles to fight against the Turtles&#39; sworn enemy, The Shredder, who has apparently teamed up with Ra&#39;s Al Ghul and The League of Assassins."
           rating="10.0" audienceRating="8.5" year="2019" tagline="Who Will Lead Them?"
           thumb="/library/metadata/48534/thumb/1601864983" art="/library/metadata/48534/art/1601864983"
           duration="5222216" originallyAvailableAt="2019-03-31" addedAt="1560006000" updatedAt="1601864983"
           audienceRatingImage="rottentomatoes://image.rating.upright" chapterSource="media"
           primaryExtraKey="/library/metadata/48535" ratingImage="rottentomatoes://image.rating.ripe">
        <Media id="73034" duration="5222216" bitrate="14110" width="1920" height="1080" aspectRatio="1.78"
               audioChannels="6" audioCodec="dca-ma" videoCodec="h264" videoResolution="1080" container="mkv"
               videoFrameRate="24p" audioProfile="ma" videoProfile="high">
            <Part id="73098" key="/library/parts/73098/1560006000/file.mkv" duration="5222216"
                  file="/data/gaps/Best Movies/Batman vs. Teenage Mutant Ninja Turtles (2019)/Batman vs. Teenage Mutant Ninja Turtles (2019).mkv"
                  size="9097120891" audioProfile="ma" container="mkv" hasThumbnail="1" indexes="sd"
                  videoProfile="high"/>
        </Media>
        <Genre tag="Action/Adventure"/>
        <Genre tag="Animation"/>
        <Director tag="Jake Castorena"/>
        <Writer tag="Marly Halpern-Graser"/>
        <Country tag="United States of America"/>
        <Role tag="Troy Baker"/>
        <Role tag="Eric Bauza"/>
        <Role tag="Darren Criss"/>
    </Video>
    <Video ratingKey="48506" key="/library/metadata/48506" guid="plex://movie/5d776b6cfb0d55001f56787f"
           studio="DC Entertainment" type="movie" title="Batman vs. Robin" contentRating="PG-13"
           summary="Damian Wayne is having a hard time coping with his father&#39;s &#34;no killing&#34; rule. Meanwhile, Gotham is going through hell with threats such as the insane Dollmaker, and the secretive Court of Owls."
           rating="10.0" audienceRating="7.8" year="2015" tagline="The showdown that will define a destiny"
           thumb="/library/metadata/48506/thumb/1601864980" art="/library/metadata/48506/art/1601864980"
           duration="4800083" originallyAvailableAt="2015-04-03" addedAt="1521903600" updatedAt="1601864980"
           audienceRatingImage="rottentomatoes://image.rating.upright" chapterSource="media"
           primaryExtraKey="/library/metadata/48533" ratingImage="rottentomatoes://image.rating.ripe">
        <Media id="72952" duration="4800083" bitrate="4504" width="1920" height="1080" aspectRatio="1.78"
               audioChannels="6" audioCodec="dca" videoCodec="h264" videoResolution="1080" container="mkv"
               videoFrameRate="24p" audioProfile="dts" videoProfile="high">
            <Part id="73016" key="/library/parts/73016/1521903600/file.mkv" duration="4800083"
                  file="/data/gaps/Best Movies/Batman vs. Robin (2015)/Batman vs. Robin (2015).mkv" size="2703877141"
                  audioProfile="dts" container="mkv" indexes="sd" videoProfile="high"/>
        </Media>
        <Genre tag="Action/Adventure"/>
        <Genre tag="Animation"/>
        <Director tag="Jay Oliva"/>
        <Writer tag="Peter Tomasi"/>
        <Writer tag="Bob Kane"/>
        <Country tag="United States of America"/>
        <Role tag="Jason O&#39;Mara"/>
        <Role tag="Stuart Allan"/>
        <Role tag="David McCallum"/>
    </Video>
    <Video ratingKey="48536" key="/library/metadata/48536" guid="plex://movie/5d776d54fb0d55001f59d6f4"
           studio="DC Entertainment" type="movie" title="Batman vs. Two-Face" contentRating="PG"
           summary="Former Gotham City District Attorney Harvey Dent, one side of his face scarred by acid, goes on a crime spree based on the number &#39;2&#39;. All of his actions are decided by the flip of a defaced, two-headed silver dollar."
           rating="10.0" audienceRating="6.0" year="2017" tagline="Everyone must face their demons."
           thumb="/library/metadata/48536/thumb/1601864987" art="/library/metadata/48536/art/1601864987"
           duration="4327914" originallyAvailableAt="2017-10-08" addedAt="1516287600" updatedAt="1601864987"
           audienceRatingImage="rottentomatoes://image.rating.upright" primaryExtraKey="/library/metadata/48540"
           ratingImage="rottentomatoes://image.rating.ripe">
        <Media id="73038" duration="4327914" bitrate="8718" width="1920" height="1080" aspectRatio="1.78"
               audioChannels="6" audioCodec="dca-ma" videoCodec="h264" videoResolution="1080" container="mkv"
               videoFrameRate="24p" audioProfile="ma" videoProfile="high">
            <Part id="73102" key="/library/parts/73102/1516287600/file.mkv" duration="4327914"
                  file="/data/gaps/Best Movies/Batman vs. Two-Face (2017)/Batman vs. Two-Face (2017).mkv"
                  size="4702621756" audioProfile="ma" container="mkv" indexes="sd" videoProfile="high"/>
        </Media>
        <Genre tag="Action/Adventure"/>
        <Genre tag="Animation"/>
        <Director tag="Rick Morales"/>
        <Writer tag="Michael Jelenic"/>
        <Writer tag="James Tucker"/>
        <Country tag="United States of America"/>
        <Role tag="Adam West"/>
        <Role tag="Burt Ward"/>
        <Role tag="William Shatner"/>
    </Video>
    <Video ratingKey="48497" key="/library/metadata/48497" guid="plex://movie/5d776c6696b655001fe2f66f"
           studio="Warner Premiere" type="movie" title="Batman: Return of the Caped Crusaders" contentRating="PG"
           summary="Adam West and Burt Ward returns to their iconic roles of Batman and Robin. The film sees the superheroes going up against classic villains like The Joker, The Riddler, The Penguin and Catwoman, both in Gotham City&#8230; and in space."
           rating="9.4" audienceRating="6.7" year="2016" tagline="The crusade continues..."
           thumb="/library/metadata/48497/thumb/1601864977" art="/library/metadata/48497/art/1601864977"
           duration="4697780" originallyAvailableAt="2016-10-11" addedAt="1549119600" updatedAt="1601864977"
           audienceRatingImage="rottentomatoes://image.rating.upright" chapterSource="media"
           primaryExtraKey="/library/metadata/48500" ratingImage="rottentomatoes://image.rating.ripe">
        <Media id="72934" duration="4697780" bitrate="7991" width="1920" height="1080" aspectRatio="1.78"
               audioChannels="6" audioCodec="dca" videoCodec="h264" videoResolution="1080" container="mkv"
               videoFrameRate="24p" audioProfile="dts" videoProfile="high">
            <Part id="72998" key="/library/parts/72998/1549119600/file.mkv" duration="4697780"
                  file="/data/gaps/Best Movies/Batman Return of the Caped Crusaders (2016)/Batman Return of the Caped Crusaders (2016).mkv"
                  size="4693797720" audioProfile="dts" container="mkv" indexes="sd" videoProfile="high"/>
        </Media>
        <Genre tag="Animation"/>
        <Genre tag="Action/Adventure"/>
        <Director tag="Rick Morales"/>
        <Writer tag="Michael Jelenic"/>
        <Writer tag="James Tucker"/>
        <Country tag="United States of America"/>
        <Role tag="Adam West"/>
        <Role tag="Burt Ward"/>
        <Role tag="Julie Newmar"/>
    </Video>
    <Video ratingKey="48498" key="/library/metadata/48498" guid="plex://movie/5d7769ac9ab54400214f5333"
           studio="DC Comics" type="movie" title="Batman: The Dark Knight Returns, Part 2" contentRating="PG-13"
           summary="Batman has stopped the reign of terror that The Mutants had cast upon his city.  Now an old foe wants a reunion and the government wants The Man of Steel to put a stop to Batman."
           audienceRating="9.4" year="2013"
           tagline="Justice Returns... Vengeance Returns... Redemption Comes to Gotham."
           thumb="/library/metadata/48498/thumb/1601864977" art="/library/metadata/48498/art/1601864977"
           duration="4549257" originallyAvailableAt="2013-01-27" addedAt="1516287600" updatedAt="1601864977"
           audienceRatingImage="rottentomatoes://image.rating.upright" primaryExtraKey="/library/metadata/48504">
        <Media id="72935" duration="4549257" bitrate="8029" width="1920" height="1080" aspectRatio="1.78"
               audioChannels="6" audioCodec="dca" videoCodec="h264" videoResolution="1080" container="mkv"
               videoFrameRate="24p" audioProfile="dts" videoProfile="high">
            <Part id="72999" key="/library/parts/72999/1516287600/file.mkv" duration="4549257"
                  file="/data/gaps/Best Movies/Batman The Dark Knight Returns, Part 2 (2013)/Batman The Dark Knight Returns, Part 2 (2013).mkv"
                  size="4567109546" audioProfile="dts" container="mkv" indexes="sd" videoProfile="high"/>
        </Media>
        <Genre tag="Animation"/>
        <Genre tag="Action/Adventure"/>
        <Director tag="Jay Oliva"/>
        <Writer tag="Frank Miller"/>
        <Writer tag="Bob Kane"/>
        <Country tag="United States of America"/>
        <Role tag="Peter Weller"/>
        <Role tag="Ariel Winter"/>
        <Role tag="David Selby"/>
    </Video>
    <Video ratingKey="48499" key="/library/metadata/48499" guid="plex://movie/5d7768740ea56a001e2a574f"
           studio="DC Comics" type="movie" title="Batman: Under the Red Hood" contentRating="PG-13"
           summary="Batman faces his ultimate challenge as the mysterious Red Hood takes Gotham City by firestorm. One part vigilante, one part criminal kingpin, Red Hood begins cleaning up Gotham with the efficiency of Batman, but without following the same ethical code."
           rating="10.0" audienceRating="9.2" year="2010" tagline="Dare to Look Beneath the Hood."
           thumb="/library/metadata/48499/thumb/1601864977" art="/library/metadata/48499/art/1601864977"
           duration="4550560" originallyAvailableAt="2010-06-10" addedAt="1516287600" updatedAt="1601864977"
           audienceRatingImage="rottentomatoes://image.rating.upright" primaryExtraKey="/library/metadata/48503"
           ratingImage="rottentomatoes://image.rating.ripe">
        <Media id="72936" duration="4550560" bitrate="8263" width="1920" height="1080" aspectRatio="1.78"
               audioChannels="6" audioCodec="ac3" videoCodec="h264" videoResolution="1080" container="mkv"
               videoFrameRate="24p" videoProfile="high">
            <Part id="73000" key="/library/parts/73000/1516287600/file.mkv" duration="4550560"
                  file="/data/gaps/Best Movies/Batman Under the Red Hood (2010)/Batman Under the Red Hood (2010).mkv"
                  size="4701095552" container="mkv" indexes="sd" videoProfile="high"/>
        </Media>
        <Genre tag="Drama"/>
        <Genre tag="Action/Adventure"/>
        <Director tag="Brandon Vietti"/>
        <Writer tag="Bob Kane"/>
        <Writer tag="Jay Oliva"/>
        <Country tag="United States of America"/>
        <Role tag="Bruce Greenwood"/>
        <Role tag="Jensen Ackles"/>
        <Role tag="Neil Patrick Harris"/>
    </Video>
    <Video ratingKey="48537" key="/library/metadata/48537" guid="plex://movie/5d7768af594b2b001e692b62"
           studio="DC Comics" type="movie" title="Batman: Year One" contentRating="PG-13"
           summary="Two men come to Gotham City: Bruce Wayne after years abroad feeding his lifelong obsession for justice and Jim Gordon after being too honest a cop with the wrong people elsewhere. After learning painful lessons about the city&#39;s corruption on its streets and police department respectively, this pair learn how to fight back their own way. With that, Gotham&#39;s evildoers from top to bottom are terrorized by the mysterious Batman and the equally heroic Gordon is assigned to catch him by comrades who both hate and fear him themselves. In the ensuing manhunt, both find much in common as the seeds of an unexpected friendship are laid with additional friends and rivals helping to start the legend."
           rating="8.8" audienceRating="7.9" year="2011" tagline="A merciless crime turns a man into an outlaw."
           thumb="/library/metadata/48537/thumb/1601864987" art="/library/metadata/48537/art/1601864987"
           duration="3849888" originallyAvailableAt="2011-10-06" addedAt="1516287600" updatedAt="1601864987"
           audienceRatingImage="rottentomatoes://image.rating.upright" chapterSource="media"
           primaryExtraKey="/library/metadata/48539" ratingImage="rottentomatoes://image.rating.ripe">
        <Media id="73039" duration="3849888" bitrate="5849" width="1920" height="1080" aspectRatio="1.78"
               audioChannels="6" audioCodec="dca" videoCodec="h264" videoResolution="1080" container="mkv"
               videoFrameRate="24p" audioProfile="dts" videoProfile="high">
            <Part id="73103" key="/library/parts/73103/1516287600/file.mkv" duration="3849888"
                  file="/data/gaps/Best Movies/Batman Year One (2011)/Batman Year One (2011).mkv" size="2816010159"
                  audioProfile="dts" container="mkv" indexes="sd" videoProfile="high"/>
        </Media>
        <Genre tag="Action/Adventure"/>
        <Genre tag="Animation"/>
        <Director tag="Lauren Montgomery"/>
        <Director tag="Sam Liu"/>
        <Writer tag="Frank Miller"/>
        <Country tag="United States of America"/>
        <Role tag="Bryan Cranston"/>
        <Role tag="Ben McKenzie"/>
        <Role tag="Eliza Dushku"/>
    </Video>
    <Video ratingKey="48538" key="/library/metadata/48538" guid="plex://movie/5d776a82594b2b001e6be438" studio="GONZO"
           type="movie" title="Bayonetta: Bloody Fate"
           originalTitle="&#12505;&#12520;&#12493;&#12483;&#12479; &#12502;&#12521;&#12483;&#12487;&#12451;&#12501;&#12455;&#12452;&#12488;"
           contentRating="TV-MA"
           summary="Bayonetta: Bloody Fate follows the story of the witch Bayonetta, as she defeats the blood-thirsty Angels and tries to remember her past from before the time she awoke, 20 years ago. Along her side are a mysterious little girl who keeps calling her &#34;Mummy&#34;, a journalist that holds a personal grudge against Bayonetta and a unknown white-haired woman who seems to know more than she is willing to reveal about Bayonetta&#39;s time before her sleep."
           audienceRating="4.6" year="2013" thumb="/library/metadata/48538/thumb/1601864988"
           art="/library/metadata/48538/art/1601864988" duration="5411456" originallyAvailableAt="2013-10-22"
           addedAt="1516287600" updatedAt="1601864988" audienceRatingImage="rottentomatoes://image.rating.spilled"
           primaryExtraKey="/library/metadata/48543">
        <Media id="73040" duration="5411456" bitrate="10408" width="1920" height="1080" aspectRatio="1.78"
               audioChannels="6" audioCodec="ac3" videoCodec="h264" videoResolution="1080" container="mkv"
               videoFrameRate="24p" videoProfile="high">
            <Part id="73104" key="/library/parts/73104/1516287600/file.mkv" duration="5411456"
                  file="/data/gaps/Best Movies/Bayonetta Bloody Fate (2013)/Bayonetta Bloody Fate (2013).mkv"
                  size="7042025410" container="mkv" indexes="sd" videoProfile="high"/>
        </Media>
        <Genre tag="Animation"/>
        <Genre tag="Action/Adventure"/>
        <Director tag="Fuminori Kizaki"/>
        <Writer tag="Mitsutaka Hirota"/>
        <Country tag="Japan"/>
        <Role tag="Atsuko Tanaka"/>
        <Role tag="Mie Sonozaki"/>
        <Role tag="Wataru Takagi"/>
    </Video>
    <Video ratingKey="48544" key="/library/metadata/48544" guid="plex://movie/5d776d19fb0d55001f597b0b"
           studio="Walt Disney Animation Studios" type="movie" title="Beauty and the Beast" contentRating="G"
           summary="Follow the adventures of Belle, a bright young woman who finds herself in the castle of a prince who&#39;s been turned into a mysterious beast. With the help of the castle&#39;s enchanted staff, Belle soon learns the most important lesson of all -- that true beauty comes from within."
           rating="9.4" audienceRating="9.2" year="1991" tagline="The most beautiful love story ever told."
           thumb="/library/metadata/48544/thumb/1601864989" art="/library/metadata/48544/art/1601864989"
           duration="5093536" originallyAvailableAt="1991-09-29" addedAt="1582988400" updatedAt="1601864989"
           audienceRatingImage="rottentomatoes://image.rating.upright" chapterSource="media"
           primaryExtraKey="/library/metadata/48545" ratingImage="rottentomatoes://image.rating.ripe">
        <Media id="73056" duration="5093536" bitrate="93191" width="3840" height="2160" aspectRatio="1.78"
               audioChannels="8" audioCodec="truehd" videoCodec="hevc" videoResolution="4k" container="mkv"
               videoFrameRate="24p" videoProfile="main 10">
            <Part id="73120" key="/library/parts/73120/1582988400/file.mkv" duration="5093536"
                  file="/data/gaps/Best Movies/Beauty and the Beast (1991)/Beauty and the Beast (1991) Remux-2160p.mkv"
                  size="59335176565" container="mkv" hasThumbnail="1" indexes="sd" videoProfile="main 10"/>
        </Media>
        <Genre tag="Romance"/>
        <Genre tag="Family"/>
        <Director tag="Gary Trousdale"/>
        <Director tag="Kirk Wise"/>
        <Writer tag="Joe Ranft"/>
        <Writer tag="Kelly Asbury"/>
        <Country tag="United States of America"/>
        <Role tag="Paige O&#39;Hara"/>
        <Role tag="Robby Benson"/>
        <Role tag="Richard White"/>
    </Video>
    <Video ratingKey="48546" key="/library/metadata/48546" guid="plex://movie/5d776b6cfb0d55001f5678b1"
           studio="Walt Disney Pictures" type="movie" title="Beauty and the Beast" contentRating="PG"
           summary="A live-action adaptation of Disney&#39;s version of the classic tale of a cursed prince and a beautiful young woman who helps him break the spell."
           rating="7.1" audienceRating="8.0" year="2017" tagline="Be our guest."
           thumb="/library/metadata/48546/thumb/1601864994" art="/library/metadata/48546/art/1601864994"
           duration="7756799" originallyAvailableAt="2017-03-15" addedAt="1591251540" updatedAt="1601864994"
           audienceRatingImage="rottentomatoes://image.rating.upright" primaryExtraKey="/library/metadata/48548"
           ratingImage="rottentomatoes://image.rating.ripe">
        <Media id="73060" duration="7756799" bitrate="67735" width="3840" height="2160" aspectRatio="1.78"
               audioChannels="2" audioCodec="aac" videoCodec="hevc" videoResolution="4k" container="mp4"
               videoFrameRate="24p" optimizedForStreaming="0" audioProfile="lc" has64bitOffsets="1"
               videoProfile="main 10">
            <Part id="73124" key="/library/parts/73124/1591251540/file.m4v" duration="7756799"
                  file="/data/gaps/Best Movies/Beauty and the Beast (2017)/Beauty and the Beast (2017) Bluray-2160p.m4v"
                  size="65715318673" audioProfile="lc" container="mp4" has64bitOffsets="1" indexes="sd"
                  optimizedForStreaming="0" videoProfile="main 10"/>
        </Media>
        <Genre tag="Musical"/>
        <Genre tag="Family"/>
        <Director tag="Bill Condon"/>
        <Writer tag="Stephen Chbosky"/>
        <Writer tag="Linda Woolverton"/>
        <Country tag="United States of America"/>
        <Role tag="Emma Watson"/>
        <Role tag="Dan Stevens"/>
        <Role tag="Luke Evans"/>
    </Video>
    <Video ratingKey="48547" key="/library/metadata/48547" guid="plex://movie/5d9f352aadeb7a0021ce130b"
           studio="Stanley Donen Films" type="movie" title="Bedazzled" contentRating="Approved"
           summary="Stanley is infatuated with Margaret, the statuesque waitress who works with him. He meets George Spiggott AKA the devil and sells his soul for 7 wishes, which Stanley uses to try and make Margaret his own first as an intellectual, then as a rock star, then as a wealthy industrialist. As each fails, he becomes more aware of how empty his life had been and how much more he has to live for."
           rating="8.2" audienceRating="7.4" year="1967"
           tagline="Peter Cook and Dudley Moore in their first starring comedy!"
           thumb="/library/metadata/48547/thumb/1601864996" art="/library/metadata/48547/art/1601864996"
           duration="6221024" originallyAvailableAt="1967-12-10" addedAt="1516287600" updatedAt="1601864996"
           audienceRatingImage="rottentomatoes://image.rating.upright" chapterSource="media"
           ratingImage="rottentomatoes://image.rating.ripe">
        <Media id="73061" duration="6221024" bitrate="6033" width="1280" height="488" aspectRatio="2.35"
               audioChannels="2" audioCodec="ac3" videoCodec="h264" videoResolution="720" container="mkv"
               videoFrameRate="24p" videoProfile="high">
            <Part id="73125" key="/library/parts/73125/1516287600/file.mkv" duration="6221024"
                  file="/data/gaps/Best Movies/Bedazzled (1967)/Bedazzled (1967).mkv" size="4693201203" container="mkv"
                  indexes="sd" videoProfile="high"/>
        </Media>
        <Genre tag="Comedy"/>
        <Genre tag="Fantasy"/>
        <Director tag="Stanley Donen"/>
        <Writer tag="Peter Cook"/>
        <Writer tag="Dudley Moore"/>
        <Country tag="United Kingdom"/>
        <Role tag="Peter Cook"/>
        <Role tag="Dudley Moore"/>
        <Role tag="Raquel Welch"/>
    </Video>
    <Video ratingKey="48588" key="/library/metadata/48588" guid="plex://movie/5d776829151a60001f24b3d0"
           studio="KirchMedia" type="movie" title="Bedazzled" contentRating="PG-13"
           summary="Elliot Richardson, a suicidal techno geek, is given seven wishes to turn his life around when he meets a very seductive Satan. The catch: his soul. Some of his wishes include a 7 foot basketball star, a rock star, and a hamburger. But, as could be expected, the Devil puts her own little twist on each of his fantasies."
           rating="5.0" audienceRating="4.2" year="2000"
           tagline="Meet the Devil. She&#39;s giving Elliott seven wishes. But not a chance in Hell."
           thumb="/library/metadata/48588/thumb/1601864997" art="/library/metadata/48588/art/1601864997"
           duration="5588583" originallyAvailableAt="2000-10-17" addedAt="1586925060" updatedAt="1601864997"
           audienceRatingImage="rottentomatoes://image.rating.spilled" chapterSource="media"
           primaryExtraKey="/library/metadata/48590" ratingImage="rottentomatoes://image.rating.rotten">
        <Media id="73182" duration="5588583" bitrate="11570" width="1920" height="1080" aspectRatio="1.78"
               audioChannels="6" audioCodec="truehd" videoCodec="hevc" videoResolution="1080" container="mkv"
               videoFrameRate="24p" videoProfile="main 10">
            <Part id="73246" key="/library/parts/73246/1586925060/file.mkv" duration="5588583"
                  file="/data/gaps/Best Movies/Bedazzled (2000)/Bedazzled 2000 Bluray-1080p.mkv" size="8130357515"
                  container="mkv" indexes="sd" videoProfile="main 10"/>
        </Media>
        <Genre tag="Comedy"/>
        <Genre tag="Fantasy"/>
        <Director tag="Harold Ramis"/>
        <Writer tag="Harold Ramis"/>
        <Writer tag="Peter Cook"/>
        <Country tag="United States of America"/>
        <Role tag="Elizabeth Hurley"/>
        <Role tag="Brendan Fraser"/>
        <Role tag="Frances O&#39;Connor"/>
    </Video>
    <Video ratingKey="48589" key="/library/metadata/48589" guid="plex://movie/5d776d1a594b2b001e7015f3"
           studio="Geffen Pictures" type="movie" title="Beetlejuice" contentRating="PG"
           summary="The spirits of a deceased couple are harassed by an unbearable family that has moved into their home, and hire a malicious spirit to drive them out."
           rating="8.4" audienceRating="8.2" year="1988"
           tagline="He&#39;s guaranteed to put some life in your afterlife."
           thumb="/library/metadata/48589/thumb/1601864998" art="/library/metadata/48589/art/1601864998"
           duration="5526395" originallyAvailableAt="1988-03-29" addedAt="1516287600" updatedAt="1601864998"
           audienceRatingImage="rottentomatoes://image.rating.upright" chapterSource="media"
           primaryExtraKey="/library/metadata/48591" ratingImage="rottentomatoes://image.rating.ripe">
        <Media id="73183" duration="5526395" bitrate="15914" width="1920" height="1080" aspectRatio="1.78"
               audioChannels="6" audioCodec="dca" videoCodec="h264" videoResolution="1080" container="mkv"
               videoFrameRate="24p" audioProfile="dts" videoProfile="high">
            <Part id="73247" key="/library/parts/73247/1516287600/file.mkv" duration="5526395"
                  file="/data/gaps/Best Movies/Beetlejuice (1988)/Beetlejuice (1988).mkv" size="10822962196"
                  audioProfile="dts" container="mkv" indexes="sd" videoProfile="high"/>
        </Media>
        <Genre tag="Fantasy"/>
        <Genre tag="Comedy"/>
        <Director tag="Tim Burton"/>
        <Writer tag="Warren Skaaren"/>
        <Writer tag="Larry Wilson"/>
        <Country tag="United States of America"/>
        <Role tag="Michael Keaton"/>
        <Role tag="Geena Davis"/>
        <Role tag="Alec Baldwin"/>
    </Video>
    <Video ratingKey="48594" key="/library/metadata/48594" guid="plex://movie/5d776826103a2d001f564156"
           studio="Gramercy Pictures" type="movie" title="Being John Malkovich" contentRating="R"
           summary="A puppeteer discovers a portal that leads literally into the head of movie star John Malkovich."
           rating="9.3" audienceRating="8.7" year="1999" tagline="Ever wanted to be someone else? Now you can."
           thumb="/library/metadata/48594/thumb/1601865002" art="/library/metadata/48594/art/1601865002"
           duration="6798836" originallyAvailableAt="1999-09-02" addedAt="1516287600" updatedAt="1601865002"
           audienceRatingImage="rottentomatoes://image.rating.upright" chapterSource="media"
           primaryExtraKey="/library/metadata/48595" ratingImage="rottentomatoes://image.rating.ripe">
        <Media id="73191" duration="6798836" bitrate="14742" width="1920" height="1036" aspectRatio="1.85"
               audioChannels="6" audioCodec="dca-ma" videoCodec="h264" videoResolution="1080" container="mkv"
               videoFrameRate="24p" audioProfile="ma" videoProfile="high">
            <Part id="73255" key="/library/parts/73255/1516287600/file.mkv" duration="6798836"
                  file="/data/gaps/Best Movies/Being John Malkovich (1999)/Being John Malkovich (1999).mkv"
                  size="12493194272" audioProfile="ma" container="mkv" indexes="sd" videoProfile="high"/>
        </Media>
        <Genre tag="Drama"/>
        <Genre tag="Fantasy"/>
        <Director tag="Spike Jonze"/>
        <Writer tag="Charlie Kaufman"/>
        <Country tag="United States of America"/>
        <Role tag="John Cusack"/>
        <Role tag="Cameron Diaz"/>
        <Role tag="Catherine Keener"/>
    </Video>
    <Video ratingKey="48597" key="/library/metadata/48597" guid="plex://movie/5d7768287e9a3c0020c6ad1f"
           studio="Metro-Goldwyn-Mayer" type="movie" title="Ben-Hur" contentRating="G"
           summary="After a Jewish prince is betrayed and sent into slavery by a Roman friend, he regains his freedom and comes back for revenge."
           rating="8.6" audienceRating="8.9" year="1959" tagline="The entertainment experience of a lifetime."
           thumb="/library/metadata/48597/thumb/1601865004" art="/library/metadata/48597/art/1601865004"
           duration="13348032" originallyAvailableAt="1959-11-18" addedAt="1516287600" updatedAt="1601865004"
           audienceRatingImage="rottentomatoes://image.rating.upright" chapterSource="media"
           primaryExtraKey="/library/metadata/48598" ratingImage="rottentomatoes://image.rating.ripe">
        <Media id="73196" duration="13348032" bitrate="18579" width="1920" height="1080" aspectRatio="1.78"
               audioChannels="6" audioCodec="dca-ma" videoCodec="h264" videoResolution="1080" container="mkv"
               videoFrameRate="24p" audioProfile="ma" videoProfile="high">
            <Part id="73260" key="/library/parts/73260/1516287600/file.mkv" duration="13348032"
                  file="/data/gaps/Best Movies/Ben-Hur (1959)/Ben-Hur (1959).mkv" size="30496788655" audioProfile="ma"
                  container="mkv" indexes="sd" videoProfile="high"/>
        </Media>
        <Genre tag="History"/>
        <Genre tag="Action/Adventure"/>
        <Director tag="William Wyler"/>
        <Writer tag="Gore Vidal"/>
        <Country tag="United States of America"/>
        <Role tag="Charlton Heston"/>
        <Role tag="Jack Hawkins"/>
        <Role tag="Haya Harareet"/>
    </Video>
    <Video ratingKey="48601" key="/library/metadata/48601" guid="plex://movie/5d776ae096b655001fdfc3ab"
           studio="Metro-Goldwyn-Mayer" type="movie" title="Ben-Hur" contentRating="PG-13"
           summary="Judah Ben-Hur, a prince falsely accused of treason by his adopted brother, an officer in the Roman army, returns to his homeland after years at sea to seek revenge, but finds redemption."
           rating="2.5" audienceRating="5.3" year="2016" tagline="First to finish. Last to die."
           thumb="/library/metadata/48601/thumb/1601865008" art="/library/metadata/48601/art/1601865008"
           duration="7483488" originallyAvailableAt="2016-08-11" addedAt="1516287600" updatedAt="1601865008"
           audienceRatingImage="rottentomatoes://image.rating.spilled" chapterSource="media"
           primaryExtraKey="/library/metadata/48604" ratingImage="rottentomatoes://image.rating.rotten">
        <Media id="73204" duration="7483488" bitrate="37789" width="1920" height="1080" aspectRatio="1.78"
               audioChannels="8" audioCodec="dca-ma" videoCodec="h264" videoResolution="1080" container="mkv"
               videoFrameRate="24p" audioProfile="ma" videoProfile="high">
            <Part id="73268" key="/library/parts/73268/1516287600/file.mkv" duration="7483488"
                  file="/data/gaps/Best Movies/Ben-Hur (2016)/Ben-Hur (2016).mkv" size="35268043582" audioProfile="ma"
                  container="mkv" hasThumbnail="1" indexes="sd" videoProfile="high"/>
        </Media>
        <Genre tag="Drama"/>
        <Genre tag="Action/Adventure"/>
        <Director tag="Timur Bekmambetov"/>
        <Writer tag="Lew Wallace"/>
        <Writer tag="John Ridley"/>
        <Country tag="United States of America"/>
        <Role tag="Jack Huston"/>
        <Role tag="Pilou Asb&#230;k"/>
        <Role tag="Rodrigo Santoro"/>
    </Video>
    <Video ratingKey="48602" key="/library/metadata/48602" guid="plex://movie/5d7769f7fb0d55001f5361eb"
           studio="Walt Disney Animation Studios" type="movie" title="Big Hero 6" contentRating="PG"
           summary="The special bond develops between plus-sized inflatable robot Baymax, and prodigy Hiro Hamada. They team up with a group of friends to form a band of high-tech heroes."
           rating="8.9" audienceRating="9.1" year="2014" tagline="From the creators of Wreck-It Ralph and Frozen."
           thumb="/library/metadata/48602/thumb/1601865010" art="/library/metadata/48602/art/1601865010"
           duration="6112768" originallyAvailableAt="2014-10-23" addedAt="1516287600" updatedAt="1601865010"
           audienceRatingImage="rottentomatoes://image.rating.upright" chapterSource="media"
           primaryExtraKey="/library/metadata/48655" ratingImage="rottentomatoes://image.rating.ripe">
        <Media id="73205" duration="6112768" bitrate="34689" width="1920" height="1080" aspectRatio="1.78"
               audioChannels="8" audioCodec="dca-ma" videoCodec="h264" videoResolution="1080" container="mkv"
               videoFrameRate="24p" audioProfile="ma" videoProfile="high">
            <Part id="73269" key="/library/parts/73269/1516287600/file.mkv" duration="6112768"
                  file="/data/gaps/Best Movies/Big Hero 6 (2014)/Big Hero 6 (2014).mkv" size="26511091779"
                  audioProfile="ma" container="mkv" indexes="sd" videoProfile="high"/>
        </Media>
        <Genre tag="Animation"/>
        <Genre tag="Action/Adventure"/>
        <Director tag="Chris Williams"/>
        <Director tag="Don Hall"/>
        <Writer tag="Daniel Gerson"/>
        <Writer tag="Robert L. Baird"/>
        <Country tag="United States of America"/>
        <Role tag="Scott Adsit"/>
        <Role tag="Ryan Potter"/>
        <Role tag="Daniel Henney"/>
    </Video>
    <Video ratingKey="48603" key="/library/metadata/48603" guid="plex://movie/5d7768313c3c2a001fbcd1f0"
           studio="TAFT Entertainment Pictures" type="movie" title="Big Trouble in Little China" contentRating="PG-13"
           summary="A rough-and-tumble trucker helps rescue his friend&#39;s fianc&#233;e from an ancient sorcerer in a supernatural battle beneath Chinatown."
           rating="7.8" audienceRating="8.2" year="1986" tagline="Adventure doesn&#39;t come any bigger!"
           thumb="/library/metadata/48603/thumb/1601865009" art="/library/metadata/48603/art/1601865009"
           duration="5987991" originallyAvailableAt="1986-07-02" addedAt="1579100400" updatedAt="1601865009"
           audienceRatingImage="rottentomatoes://image.rating.upright" chapterSource="media"
           primaryExtraKey="/library/metadata/48652" ratingImage="rottentomatoes://image.rating.ripe">
        <Media id="73206" duration="5987991" bitrate="11399" width="1920" height="816" aspectRatio="2.35"
               audioChannels="6" audioCodec="dca" videoCodec="h264" videoResolution="1080" container="mkv"
               videoFrameRate="24p" audioProfile="dts" videoProfile="high">
            <Part id="73270" key="/library/parts/73270/1579100400/file.mkv" duration="5987991"
                  file="/data/gaps/Best Movies/Big Trouble in Little China (1986)/Big Trouble in Little China (1986) Bluray-1080p.mkv"
                  size="8535077637" audioProfile="dts" container="mkv" indexes="sd" videoProfile="high"/>
        </Media>
        <Genre tag="Comedy"/>
        <Genre tag="Fantasy"/>
        <Director tag="John Carpenter"/>
        <Writer tag="W.D. Richter"/>
        <Writer tag="David Z. Weinstein"/>
        <Country tag="United States of America"/>
        <Role tag="Kurt Russell"/>
        <Role tag="Kim Cattrall"/>
        <Role tag="Dennis Dun"/>
    </Video>
    <Video ratingKey="48651" key="/library/metadata/48651" guid="plex://movie/5d776829eb5d26001f1de247"
           studio="Orion Pictures" type="movie" title="Bill &amp; Ted&#39;s Bogus Journey" contentRating="PG"
           summary="A tyrant from the future creates evil android doubles of Bill and Ted and sends them back to eliminate the originals."
           rating="5.7" audienceRating="5.6" year="1991" tagline="Once... they made history. Now... they are history."
           thumb="/library/metadata/48651/thumb/1601865011" art="/library/metadata/48651/art/1601865011"
           duration="5634009" originallyAvailableAt="1991-07-19" addedAt="1516287600" updatedAt="1601865011"
           audienceRatingImage="rottentomatoes://image.rating.spilled" chapterSource="media"
           primaryExtraKey="/library/metadata/48680" ratingImage="rottentomatoes://image.rating.rotten">
        <Media id="73348" duration="5634009" bitrate="5078" width="1916" height="1032" aspectRatio="1.85"
               audioChannels="2" audioCodec="aac" videoCodec="h264" videoResolution="1080" container="mp4"
               videoFrameRate="24p" optimizedForStreaming="1" audioProfile="lc" has64bitOffsets="0"
               videoProfile="constrained baseline">
            <Part id="73412" key="/library/parts/73412/1516287600/file.mp4" duration="5634009"
                  file="/data/gaps/Best Movies/Bill &amp; Ted&#39;s Bogus Journey (1991)/Bill &amp; Ted&#39;s Bogus Journey (1991).mp4"
                  size="3580239907" audioProfile="lc" container="mp4" has64bitOffsets="0" hasThumbnail="1" indexes="sd"
                  optimizedForStreaming="1" videoProfile="constrained baseline"/>
        </Media>
        <Genre tag="Comedy"/>
        <Genre tag="Action/Adventure"/>
        <Director tag="Peter Hewitt"/>
        <Writer tag="Ed Solomon"/>
        <Writer tag="Chris Matheson"/>
        <Country tag="United States of America"/>
        <Role tag="Keanu Reeves"/>
        <Role tag="Alex Winter"/>
        <Role tag="William Sadler"/>
    </Video>
    <Video ratingKey="48653" key="/library/metadata/48653" guid="plex://movie/5d77682a3c3c2a001fbcbcbf"
           studio="Orion Pictures" type="movie" title="Bill &amp; Ted&#39;s Excellent Adventure" contentRating="PG"
           summary="Two seemingly dumb teens set off on a quest to prepare the ultimate historical presentation with the help of a time machine."
           rating="8.1" audienceRating="7.5" year="1989"
           tagline="History is about to be rewritten by two guys who can&#39;t spell."
           thumb="/library/metadata/48653/thumb/1601865012" art="/library/metadata/48653/art/1601865012"
           duration="5391385" originallyAvailableAt="1989-02-17" addedAt="1516287600" updatedAt="1601865012"
           audienceRatingImage="rottentomatoes://image.rating.upright" chapterSource="media"
           primaryExtraKey="/library/metadata/48688" ratingImage="rottentomatoes://image.rating.ripe">
        <Media id="73351" duration="5391385" bitrate="10443" width="1920" height="816" aspectRatio="2.35"
               audioChannels="6" audioCodec="dca" videoCodec="h264" videoResolution="1080" container="mkv"
               videoFrameRate="24p" audioProfile="dts" videoProfile="high">
            <Part id="73415" key="/library/parts/73415/1516287600/file.mkv" duration="5391385"
                  file="/data/gaps/Best Movies/Bill &amp; Ted&#39;s Excellent Adventure (1989)/Bill &amp; Ted&#39;s Excellent Adventure (1989).mkv"
                  size="7039207617" audioProfile="dts" container="mkv" indexes="sd" videoProfile="high"/>
        </Media>
        <Genre tag="Comedy"/>
        <Genre tag="Action/Adventure"/>
        <Director tag="Stephen Herek"/>
        <Writer tag="Ed Solomon"/>
        <Writer tag="Chris Matheson"/>
        <Country tag="United States of America"/>
        <Role tag="Keanu Reeves"/>
        <Role tag="Alex Winter"/>
        <Role tag="George Carlin"/>
    </Video>
    <Video ratingKey="48654" key="/library/metadata/48654" guid="plex://movie/5d77686954c0f0001f30806a"
           studio="Marvel Enterprises" type="movie" title="Blade" contentRating="R"
           summary="A half-vampire, half-mortal man becomes a protector of the mortal race, while slaying evil vampires."
           rating="5.5" audienceRating="7.8" year="1998" tagline="Part Man. Part Vampire. All Hero."
           thumb="/library/metadata/48654/thumb/1601865012" art="/library/metadata/48654/art/1601865012"
           duration="7213554" originallyAvailableAt="1998-08-19" addedAt="1516287600" updatedAt="1601865012"
           audienceRatingImage="rottentomatoes://image.rating.upright" primaryExtraKey="/library/metadata/48686"
           ratingImage="rottentomatoes://image.rating.rotten">
        <Media id="73352" duration="7213554" bitrate="14199" width="1920" height="1080" aspectRatio="1.78"
               audioChannels="6" audioCodec="dca" videoCodec="h264" videoResolution="1080" container="mkv"
               videoFrameRate="24p" audioProfile="dts" videoProfile="high">
            <Part id="73416" key="/library/parts/73416/1516287600/file.mkv" duration="7213554"
                  file="/data/gaps/Best Movies/Blade (1998)/Blade (1998).mkv" size="12805095497" audioProfile="dts"
                  container="mkv" indexes="sd" videoProfile="high"/>
        </Media>
        <Genre tag="Action/Adventure"/>
        <Genre tag="Sci-Fi"/>
        <Director tag="Stephen Norrington"/>
        <Writer tag="David S. Goyer"/>
        <Country tag="United States of America"/>
        <Role tag="Wesley Snipes"/>
        <Role tag="Stephen Dorff"/>
        <Role tag="Kris Kristofferson"/>
    </Video>
    <Video ratingKey="48679" key="/library/metadata/48679" guid="plex://movie/5d776868eb5d26001f1ea0ae"
           studio="Marvel Enterprises" type="movie" title="Blade II" contentRating="R"
           summary="Blade forms an uneasy alliance with the vampire council in order to combat the Reapers, who are feeding on vampires."
           rating="5.7" audienceRating="6.8" year="2002" tagline="Faster. Sharper. Deadlier."
           thumb="/library/metadata/48679/thumb/1601865013" art="/library/metadata/48679/art/1601865013"
           duration="7010011" originallyAvailableAt="2002-03-21" addedAt="1516287600" updatedAt="1601865013"
           audienceRatingImage="rottentomatoes://image.rating.upright" primaryExtraKey="/library/metadata/48697"
           ratingImage="rottentomatoes://image.rating.rotten">
        <Media id="73425" duration="7010011" bitrate="13473" width="1920" height="1078" aspectRatio="1.78"
               audioChannels="6" audioCodec="dca" videoCodec="h264" videoResolution="1080" container="mkv"
               videoFrameRate="24p" audioProfile="dts" videoProfile="high">
            <Part id="73489" key="/library/parts/73489/1516287600/file.mkv" duration="7010011"
                  file="/data/gaps/Best Movies/Blade II (2002)/Blade II (2002).mkv" size="11807845249"
                  audioProfile="dts" container="mkv" indexes="sd" videoProfile="high"/>
        </Media>
        <Genre tag="Sci-Fi"/>
        <Genre tag="Horror"/>
        <Director tag="Guillermo del Toro"/>
        <Writer tag="David S. Goyer"/>
        <Country tag="United States of America"/>
        <Role tag="Wesley Snipes"/>
        <Role tag="Kris Kristofferson"/>
        <Role tag="Ron Perlman"/>
    </Video>
    <Video ratingKey="48696" key="/library/metadata/48696" guid="plex://movie/5d7768245af944001f1f6282"
           studio="Shaw Brothers" type="movie" title="Blade Runner" contentRating="R"
           summary="A blade runner must pursue and terminate four replicants who stole a ship in space, and have returned to Earth to find their creator."
           rating="9.0" audienceRating="9.1" year="1982" tagline="Man has made his match... now it&#39;s his problem."
           thumb="/library/metadata/48696/thumb/1601865015" art="/library/metadata/48696/art/1601865015"
           duration="7056864" originallyAvailableAt="1982-06-25" addedAt="1516287600" updatedAt="1601865015"
           audienceRatingImage="rottentomatoes://image.rating.upright" chapterSource="media"
           primaryExtraKey="/library/metadata/48699" ratingImage="rottentomatoes://image.rating.ripe">
        <Media id="73467" duration="7056864" bitrate="18543" width="1920" height="1080" aspectRatio="1.78"
               audioChannels="6" audioCodec="truehd" videoCodec="h264" videoResolution="1080" container="mkv"
               videoFrameRate="24p" videoProfile="high">
            <Part id="73531" key="/library/parts/73531/1516287600/file.mkv" duration="7056864"
                  file="/data/gaps/Best Movies/Blade Runner (1982)/Blade Runner (1982).mkv" size="16419392562"
                  container="mkv" indexes="sd" videoProfile="high"/>
        </Media>
        <Genre tag="Sci-Fi"/>
        <Genre tag="Drama"/>
        <Director tag="Ridley Scott"/>
        <Writer tag="Philip K. Dick"/>
        <Writer tag="Hampton Fancher"/>
        <Country tag="United States of America"/>
        <Country tag="Hong Kong"/>
        <Role tag="Harrison Ford"/>
        <Role tag="Rutger Hauer"/>
        <Role tag="Sean Young"/>
    </Video>
    <Video ratingKey="48704" key="/library/metadata/48704" guid="plex://movie/5d776b95594b2b001e6de3f3"
           studio="Torridon Films" type="movie" title="Blade Runner 2049" contentRating="R"
           summary="Young Blade Runner K&#39;s discovery of a long-buried secret leads him to track down former Blade Runner Rick Deckard, who&#39;s been missing for thirty years."
           rating="8.8" audienceRating="8.1" year="2017" tagline="The key to the future is finally unearthed."
           thumb="/library/metadata/48704/thumb/1601865018" art="/library/metadata/48704/art/1601865018"
           duration="9827840" originallyAvailableAt="2017-10-03" addedAt="1579273200" updatedAt="1601865018"
           audienceRatingImage="rottentomatoes://image.rating.upright" chapterSource="media"
           primaryExtraKey="/library/metadata/48719" ratingImage="rottentomatoes://image.rating.ripe">
        <Media id="73479" duration="9827840" bitrate="35745" width="1920" height="1080" aspectRatio="1.78"
               audioChannels="8" audioCodec="truehd" videoCodec="h264" videoResolution="1080" container="mkv"
               videoFrameRate="24p" videoProfile="high">
            <Part id="73543" key="/library/parts/73543/1579273200/file.mkv" duration="9827840"
                  file="/data/gaps/Best Movies/Blade Runner 2049 (2017)/Blade Runner 2049 (2017) Remux-1080p.mkv"
                  size="43960440606" container="mkv" hasThumbnail="1" indexes="sd" videoProfile="high"/>
        </Media>
        <Genre tag="Sci-Fi"/>
        <Genre tag="Thriller"/>
        <Director tag="Denis Villeneuve"/>
        <Writer tag="Philip K. Dick"/>
        <Writer tag="Hampton Fancher"/>
        <Country tag="Canada"/>
        <Country tag="Hungary"/>
        <Role tag="Ryan Gosling"/>
        <Role tag="Ana de Armas"/>
        <Role tag="Jared Leto"/>
    </Video>
    <Video ratingKey="48705" key="/library/metadata/48705" guid="plex://movie/5d77686954c0f0001f30806e"
           studio="Marvel Enterprises" type="movie" title="Blade: Trinity" contentRating="R"
           summary="Blade, now a wanted man by the FBI, must join forces with the Nightstalkers to face his most challenging enemy yet: Dracula."
           rating="2.6" audienceRating="5.9" year="2004" tagline="The final hunt begins."
           thumb="/library/metadata/48705/thumb/1601865017" art="/library/metadata/48705/art/1601865017"
           duration="6772870" originallyAvailableAt="2004-11-11" addedAt="1516287600" updatedAt="1601865017"
           audienceRatingImage="rottentomatoes://image.rating.spilled" primaryExtraKey="/library/metadata/48706"
           ratingImage="rottentomatoes://image.rating.rotten">
        <Media id="73480" duration="6772870" bitrate="12678" width="1916" height="814" aspectRatio="2.35"
               audioChannels="6" audioCodec="dca" videoCodec="h264" videoResolution="1080" container="mkv"
               videoFrameRate="24p" audioProfile="dts" videoProfile="high">
            <Part id="73544" key="/library/parts/73544/1516287600/file.mkv" duration="6772870"
                  file="/data/gaps/Best Movies/Blade Trinity (2004)/Blade Trinity (2004).mkv" size="10735555436"
                  audioProfile="dts" container="mkv" indexes="sd" videoProfile="high"/>
        </Media>
        <Genre tag="Action/Adventure"/>
        <Genre tag="Sci-Fi"/>
        <Director tag="David S. Goyer"/>
        <Writer tag="David S. Goyer"/>
        <Country tag="United States of America"/>
        <Role tag="Wesley Snipes"/>
        <Role tag="Kris Kristofferson"/>
        <Role tag="Dominic Purcell"/>
    </Video>
    <Video ratingKey="48718" key="/library/metadata/48718" guid="plex://movie/5d7768364de0ee001fccbab2"
           studio="Crossbow Productions" type="movie" title="Blazing Saddles" contentRating="R"
           summary="In order to ruin a western town, a corrupt politician appoints a black Sheriff, who promptly becomes his most formidable adversary."
           rating="8.8" audienceRating="9.1" year="1974" tagline="Never give a saga an even break!"
           thumb="/library/metadata/48718/thumb/1601865020" art="/library/metadata/48718/art/1601865020"
           duration="5574610" originallyAvailableAt="1974-02-07" addedAt="1516287600" updatedAt="1601865020"
           audienceRatingImage="rottentomatoes://image.rating.upright" primaryExtraKey="/library/metadata/48731"
           ratingImage="rottentomatoes://image.rating.ripe">
        <Media id="73505" duration="5574610" bitrate="17756" width="1920" height="806" aspectRatio="2.35"
               audioChannels="6" audioCodec="dca-ma" videoCodec="h264" videoResolution="1080" container="mkv"
               videoFrameRate="24p" audioProfile="ma" videoProfile="high">
            <Part id="73569" key="/library/parts/73569/1516287600/file.mkv" duration="5574610"
                  file="/data/gaps/Best Movies/Blazing Saddles (1974)/Blazing Saddles (1974).mkv" size="12378110903"
                  audioProfile="ma" container="mkv" indexes="sd" videoProfile="high"/>
        </Media>
        <Genre tag="Comedy"/>
        <Genre tag="Western"/>
        <Director tag="Mel Brooks"/>
        <Writer tag="Richard Pryor"/>
        <Writer tag="Mel Brooks"/>
        <Country tag="United States of America"/>
        <Role tag="Cleavon Little"/>
        <Role tag="Gene Wilder"/>
        <Role tag="Slim Pickens"/>
    </Video>
</MediaContainer>
